{"transfers":[{"element_in":146,"element_in_cost":38,"element_out":42,"element_out_cost":49,"entry":4206643,"event":32,"time":"2021-04-16T10:37:59.303466Z"},{"element_in":67,"element_in_cost":44,"element_out":451,"element_out_cost":43,"entry":4206643,"event":32,"time":"2021-04-16T10:37:59.302826Z"},{"element_in":93,"element_in_cost":48,"element_out":202,"element_out_cost":64,"entry":4206643,"event":32,"time":"2021-04-16T10:37:59.302184Z"},{"element_in":548,"element_in_cost":52,"element_out":12,"element_out_cost":49,"entry":4206643,"event":32,"time":"2021-04-16T10:37:59.301542Z"},{"element_in":233,"element_in_cost":60,"element_out":164,"element_out_cost":74,"entry":4206643,"event":32,"time":"2021-04-16T10:37:59.300917Z"},{"element_in":254,"element_in_cost":125,"element_out":271,"element_out_cost":56,"entry":4206643,"event":32,"time":"2021-04-16T10:37:59.300299Z"},{"element_in":542,"element_in_cost":55,"element_out":435,"element_out_cost":56,"entry":4206643,"event":32,"time":"2021-04-16T10:37:59.299677Z"},{"element_in":102,"element_in_cost":59,"element_out":277,"element_out_cost":60,"entry":4206643,"event":32,"time":"2021-04-16T10:37:59.299079Z"},{"element_in":576,"element_in_cost":45,"element_out":273,"element_out_cost":51,"entry":4206643,"event":32,"time":"2021-04-16T10:37:59.298580Z"},{"element_in":523,"element_in_cost":40,"element_out":96,"element_out_cost":55,"entry":4206643,"event":32,"time":"2021-04-16T10:37:59.298158Z"},{"element_in":468,"element_in_cost":69,"element_out":236,"element_out_cost":48,"entry":4206643,"event":31,"time":"2021-04-09T13:06:10.144301Z"},{"element_in":301,"element_in_cost":63,"element_out":543,"element_out_cost":93,"entry":4206643,"event":31,"time":"2021-04-09T13:06:10.130355Z"},{"element_in":200,"element_in_cost":51,"element_out":451,"element_out_cost":43,"entry":4206643,"event":29,"time":"2021-03-19T17:56:48.727081Z"},{"element_in":571,"element_in_cost":45,"element_out":42,"element_out_cost":50,"entry":4206643,"event":29,"time":"2021-03-19T17:56:48.726773Z"},{"element_in":557,"element_in_cost":51,"element_out":236,"element_out_cost":48,"entry":4206643,"event":29,"time":"2021-03-19T17:56:48.726425Z"},{"element_in":213,"element_in_cost":46,"element_out":96,"element_out_cost":55,"entry":4206643,"event":29,"time":"2021-03-19T17:56:48.726096Z"},{"element_in":68,"element_in_cost":61,"element_out":164,"element_out_cost":75,"entry":4206643,"event":29,"time":"2021-03-19T17:56:48.725792Z"},{"element_in":437,"element_in_cost":67,"element_out":202,"element_out_cost":65,"entry":4206643,"event":29,"time":"2021-03-19T17:56:48.725456Z"},{"element_in":392,"element_in_cost":66,"element_out":390,"element_out_cost":94,"entry":4206643,"event":29,"time":"2021-03-19T17:56:48.725100Z"},{"element_in":570,"element_in_cost":56,"element_out":302,"element_out_cost":110,"entry":4206643,"event":29,"time":"2021-03-19T17:56:48.724770Z"},{"element_in":69,"element_in_cost":58,"element_out":271,"element_out_cost":58,"entry":4206643,"event":29,"time":"2021-03-19T17:56:48.724424Z"},{"element_in":562,"element_in_cost":46,"element_out":277,"element_out_cost":60,"entry":4206643,"event":29,"time":"2021-03-19T17:56:48.724047Z"},{"element_in":558,"element_in_cost":46,"element_out":273,"element_out_cost":51,"entry":4206643,"event":29,"time":"2021-03-19T17:56:48.723716Z"},{"element_in":597,"element_in_cost":45,"element_out":12,"element_out_cost":49,"entry":4206643,"event":29,"time":"2021-03-19T17:56:48.723240Z"},{"element_in":451,"element_in_cost":43,"element_out":155,"element_out_cost":61,"entry":4206643,"event":28,"time":"2021-03-12T12:52:25.308949Z"},{"element_in":543,"element_in_cost":95,"element_out":449,"element_out_cost":52,"entry":4206643,"event":28,"time":"2021-03-12T12:52:25.307685Z"},{"element_in":236,"element_in_cost":48,"element_out":120,"element_out_cost":69,"entry":4206643,"event":28,"time":"2021-03-12T12:52:25.298426Z"},{"element_in":120,"element_in_cost":68,"element_out":235,"element_out_cost":69,"entry":4206643,"event":27,"time":"2021-03-05T17:37:54.803241Z"},{"element_in":42,"element_in_cost":49,"element_out":239,"element_out_cost":47,"entry":4206643,"event":26,"time":"2021-02-26T12:57:07.299081Z"},{"element_in":155,"element_in_cost":61,"element_out":255,"element_out_cost":71,"entry":4206643,"event":24,"time":"2021-02-13T10:29:06.213728Z"},{"element_in":96,"element_in_cost":55,"element_out":363,"element_out_cost":45,"entry":4206643,"event":24,"time":"2021-02-13T10:29:06.205960Z"},{"element_in":277,"element_in_cost":60,"element_out":232,"element_out_cost":59,"entry":4206643,"event":23,"time":"2021-02-05T18:04:27.816367Z"},{"element_in":235,"element_in_cost":69,"element_out":284,"element_out_cost":62,"entry":4206643,"event":22,"time":"2021-02-02T12:13:19.376179Z"},{"element_in":435,"element_in_cost":55,"element_out":110,"element_out_cost":57,"entry":4206643,"event":21,"time":"2021-01-29T17:46:53.499296Z"},{"element_in":284,"element_in_cost":63,"element_out":105,"element_out_cost":47,"entry":4206643,"event":19,"time":"2021-01-15T18:05:30.999126Z"},{"element_in":271,"element_in_cost":54,"element_out":37,"element_out_cost":77,"entry":4206643,"event":18,"time":"2021-01-12T12:47:05.189103Z"},{"element_in":273,"element_in_cost":50,"element_out":452,"element_out_cost":39,"entry":4206643,"event":18,"time":"2021-01-11T13:58:01.839971Z"},{"element_in":37,"element_in_cost":77,"element_out":275,"element_out_cost":82,"entry":4206643,"event":17,"time":"2021-01-01T10:48:33.015542Z"},{"element_in":202,"element_in_cost":64,"element_out":377,"element_out_cost":60,"entry":4206643,"event":16,"time":"2020-12-27T18:13:52.716841Z"},{"element_in":449,"element_in_cost":51,"element_out":370,"element_out_cost":63,"entry":4206643,"event":16,"time":"2020-12-27T18:13:52.710066Z"},{"element_in":363,"element_in_cost":46,"element_out":32,"element_out_cost":40,"entry":4206643,"event":14,"time":"2020-12-18T11:56:05.240670Z"},{"element_in":377,"element_in_cost":60,"element_out":202,"element_out_cost":60,"entry":4206643,"event":13,"time":"2020-12-14T11:50:34.821464Z"},{"element_in":370,"element_in_cost":63,"element_out":468,"element_out_cost":68,"entry":4206643,"event":13,"time":"2020-12-14T11:17:25.325797Z"},{"element_in":110,"element_in_cost":57,"element_out":277,"element_out_cost":55,"entry":4206643,"event":12,"time":"2020-12-11T17:50:38.371933Z"},{"element_in":275,"element_in_cost":83,"element_out":508,"element_out_cost":76,"entry":4206643,"event":11,"time":"2020-12-04T19:17:17.866532Z"},{"element_in":468,"element_in_cost":67,"element_out":141,"element_out_cost":72,"entry":4206643,"event":10,"time":"2020-11-27T17:14:18.692215Z"},{"element_in":277,"element_in_cost":55,"element_out":146,"element_out_cost":40,"entry":4206643,"event":10,"time":"2020-11-27T17:14:18.685993Z"},{"element_in":302,"element_in_cost":106,"element_out":254,"element_out_cost":121,"entry":4206643,"event":9,"time":"2020-11-20T17:12:10.727690Z"},{"element_in":232,"element_in_cost":59,"element_out":467,"element_out_cost":40,"entry":4206643,"event":8,"time":"2020-11-05T12:34:35.817682Z"},{"element_in":202,"element_in_cost":59,"element_out":166,"element_out_cost":78,"entry":4206643,"event":7,"time":"2020-10-30T16:32:01.084646Z"},{"element_in":390,"element_in_cost":94,"element_out":76,"element_out_cost":45,"entry":4206643,"event":6,"time":"2020-10-23T15:29:33.494657Z"},{"element_in":452,"element_in_cost":40,"element_out":457,"element_out_cost":58,"entry":4206643,"event":6,"time":"2020-10-23T15:29:33.494002Z"},{"element_in":467,"element_in_cost":40,"element_out":259,"element_out_cost":75,"entry":4206643,"event":6,"time":"2020-10-23T15:29:33.484591Z"},{"element_in":32,"element_in_cost":40,"element_out":35,"element_out_cost":40,"entry":4206643,"event":5,"time":"2020-10-16T16:52:04.487168Z"},{"element_in":166,"element_in_cost":80,"element_out":50,"element_out_cost":45,"entry":4206643,"event":4,"time":"2020-10-02T16:40:13.757383Z"},{"element_in":141,"element_in_cost":72,"element_out":390,"element_out_cost":90,"entry":4206643,"event":4,"time":"2020-10-02T16:40:13.628684Z"},{"element_in":164,"element_in_cost":74,"element_out":117,"element_out_cost":94,"entry":4206643,"event":4,"time":"2020-09-27T08:08:59.835812Z"},{"element_in":12,"element_in_cost":45,"element_out":363,"element_out_cost":45,"entry":4206643,"event":3,"time":"2020-09-25T15:43:50.676485Z"},{"element_in":146,"element_in_cost":40,"element_out":375,"element_out_cost":45,"entry":4206643,"event":2,"time":"2020-09-18T16:41:18.228702Z"},{"element_in":76,"element_in_cost":45,"element_out":427,"element_out_cost":50,"entry":4206643,"event":2,"time":"2020-09-18T16:41:18.226290Z"},{"element_in":50,"element_in_cost":45,"element_out":366,"element_out_cost":85,"entry":4206643,"event":2,"time":"2020-09-18T16:41:18.223537Z"},{"element_in":105,"element_in_cost":50,"element_out":338,"element_out_cost":55,"entry":4206643,"event":2,"time":"2020-09-18T16:41:18.219517Z"},{"element_in":254,"element_in_cost":120,"element_out":465,"element_out_cost":65,"entry":4206643,"event":2,"time":"2020-09-18T16:41:18.217236Z"}]}